aadioptimize/__init__.py
aadioptimize/optimize.py
funcs/__init__.py
funcs/funcs.py
aadioptimize-0.0.3.dist-info/LICENSE
aadioptimize-0.0.3.dist-info/METADATA
aadioptimize-0.0.3.dist-info/WHEEL
aadioptimize-0.0.3.dist-info/top_level.txt
aadioptimize-0.0.3.dist-info/RECORD
