Metadata-Version: 2.1
Name: aadioptimize
Version: 0.0.3
Summary: Perform optimization for function
Home-page: https://github.com/aaditep/aadioptimize
Author: Aadi Tepper
Author-email: aaditep@gmail.com
License: MIT
Platform: UNKNOWN
Requires-Python: >=3.7
Requires-Dist: numpy
